{
  "1": {
    "text": "commit",
    "isDone": false
  },
  "2": {
    "text": "eat",
    "isDone": false
  },
  "3": {
    "text": "do some sport",
    "isDone": false
  },
  "4": {
    "text": "draw",
    "isDone": false
  },
  "5": {
    "text": "plop",
    "isDone": false
  },
  "6": {
    "text": "ih",
    "isDone": false
  },
  "7": {
    "text": "ih",
    "isDone": false
  },
  "8": {
    "text": "drink",
    "isDone": false
  },
  "9": {
    "text": "your",
    "isDone": false
  },
  "10": {
    "text": "water",
    "isDone": false
  },
  "11": {
    "text": "another one",
    "isDone": false
  }
}